{"cameraMode":{"drawMode":0,"name":"Shaded","section":"Shading Mode"},"sceneLighting":true,"audioPlay":false,"sceneViewState":{"m_AlwaysRefresh":false,"showFog":true,"showSkybox":true,"showFlares":true,"showImageEffects":true,"showParticleSystems":true,"showVisualEffectGraphs":true,"m_FxEnabled":true},"in2DMode":false,"pivot":{"x":6.891384124755859,"y":2.8436036109924318,"z":-28.12375259399414},"rotation":{"x":-0.100505031645298,"y":0.44744691252708437,"z":-0.05071265250444412,"w":-0.8872299194335938},"size":10.983770370483399,"orthographic":false}